horalog_cli/__init__.py
horalog_cli/journal.py
horalog_cli/main.py
horalog_cli/review.py
horalog_cli/utils.py
horalog_cli-1.0.1.dist-info/licenses/LICENSE
scripts/__init__.py
scripts/build.py
scripts/test.py
scripts/upload.py
horalog_cli-1.0.1.dist-info/METADATA
horalog_cli-1.0.1.dist-info/WHEEL
horalog_cli-1.0.1.dist-info/entry_points.txt
horalog_cli-1.0.1.dist-info/top_level.txt
horalog_cli-1.0.1.dist-info/RECORD
